{"datastore": "local", "version": "1.0", "attempt": 0, "python_version": "3.8.9 (default, Oct 26 2021, 07:25:53) \n[Clang 13.0.0 (clang-1300.0.29.30)]", "objects": {"name": "57372c6897df50ef17100fd63bad09d08d51748a", "mapping": "030e33b912fdd62c4c0e2fa86bb663c81c52294c", "_transition": "abffd6d0d822486e7bb43971dff7b656c0c76a4a", "_task_ok": "69e77141c3eb7a8c9ce864251d70c02723f29332", "_success": "69e77141c3eb7a8c9ce864251d70c02723f29332", "_foreach_stack": "4ca058df2ea422cca260c585409d6ac9face7ebe", "_foreach_var": "f3627f46179fdd95bf0e83101840fd1d71b60e40", "_foreach_num_splits": "f3627f46179fdd95bf0e83101840fd1d71b60e40", "_exception": "f3627f46179fdd95bf0e83101840fd1d71b60e40", "_current_step": "01b168d0b2c70f906b295772af9efb98b0797cae"}, "info": {"name": {"size": 27, "type": "<class 'str'>", "encoding": "gzip+pickle-v2"}, "mapping": {"size": 33, "type": "<class 'dict'>", "encoding": "gzip+pickle-v2"}, "_transition": {"size": 22, "type": "<class 'tuple'>", "encoding": "gzip+pickle-v2"}, "_task_ok": {"size": 4, "type": "<class 'bool'>", "encoding": "gzip+pickle-v2"}, "_success": {"size": 4, "type": "<class 'bool'>", "encoding": "gzip+pickle-v2"}, "_foreach_stack": {"size": 6, "type": "<class 'list'>", "encoding": "gzip+pickle-v2"}, "_foreach_var": {"size": 4, "type": "<class 'NoneType'>", "encoding": "gzip+pickle-v2"}, "_foreach_num_splits": {"size": 4, "type": "<class 'NoneType'>", "encoding": "gzip+pickle-v2"}, "_exception": {"size": 4, "type": "<class 'NoneType'>", "encoding": "gzip+pickle-v2"}, "_current_step": {"size": 15, "type": "<class 'str'>", "encoding": "gzip+pickle-v2"}}}